dagster_snowflake_pyspark/__init__.py
dagster_snowflake_pyspark/constants.py
dagster_snowflake_pyspark/py.typed
dagster_snowflake_pyspark/snowflake_pyspark_type_handler.py
dagster_snowflake_pyspark/version.py
dagster_snowflake_pyspark-0.28.13.dist-info/licenses/LICENSE
dagster_snowflake_pyspark-0.28.13.dist-info/METADATA
dagster_snowflake_pyspark-0.28.13.dist-info/WHEEL
dagster_snowflake_pyspark-0.28.13.dist-info/top_level.txt
dagster_snowflake_pyspark-0.28.13.dist-info/RECORD
