Metadata-Version: 2.4
Name: dagster-snowflake-pyspark
Version: 0.28.13
Summary: Package for integrating Snowflake and PySpark with Dagster.
Home-page: https://github.com/dagster-io/dagster/tree/master/python_modules/libraries/dagster-snowflake-pyspark
Author: Dagster Labs
Author-email: hello@dagsterlabs.com
License: Apache-2.0
Classifier: Programming Language :: Python :: 3.10
Classifier: License :: OSI Approved :: Apache Software License
Classifier: Operating System :: OS Independent
Requires-Python: >=3.10,<3.14
License-File: LICENSE
Requires-Dist: dagster==1.12.13
Requires-Dist: dagster-snowflake==0.28.13
Requires-Dist: pyspark<4
Requires-Dist: requests
Requires-Dist: sqlalchemy!=1.4.42
Requires-Dist: snowflake-sqlalchemy>=1.2
Dynamic: author
Dynamic: author-email
Dynamic: classifier
Dynamic: home-page
Dynamic: license
Dynamic: license-file
Dynamic: requires-dist
Dynamic: requires-python
Dynamic: summary
